{
  "version": "7",
  "dialect": "postgresql",
  "entries": [
    {
      "idx": 0,
      "version": "7",
      "when": 1730322272953,
      "tag": "0000_colossal_sprite",
      "breakpoints": true
    },
    {
      "idx": 1,
      "version": "7",
      "when": 1730323328261,
      "tag": "0001_cultured_tomorrow_man",
      "breakpoints": true
    },
    {
      "idx": 2,
      "version": "7",
      "when": 1730400908286,
      "tag": "0002_dashing_lily_hollister",
      "breakpoints": true
    },
    {
      "idx": 3,
      "version": "7",
      "when": 1730400988942,
      "tag": "0003_puzzling_pride",
      "breakpoints": true
    },
    {
      "idx": 4,
      "version": "7",
      "when": 1730404952823,
      "tag": "0004_freezing_gorilla_man",
      "breakpoints": true
    }
  ]
}